forklib/__init__.py
forklib/forking.py
forklib/iterator.py
forklib-0.5.0.dist-info/LICENSE
forklib-0.5.0.dist-info/METADATA
forklib-0.5.0.dist-info/WHEEL
forklib-0.5.0.dist-info/top_level.txt
forklib-0.5.0.dist-info/RECORD
