Metadata-Version: 2.1
Name: forklib
Version: 0.5.0
Summary: Fork the single process easily
Home-page: UNKNOWN
Author: Dmitry Orlov
Author-email: me@mosquito.su
Maintainer: Dmitry Orlov
Maintainer-email: me@mosquito.su
License: Apache 2
Platform: posix
Classifier: Environment :: Console
Classifier: Intended Audience :: Developers
Classifier: Intended Audience :: System Administrators
Classifier: License :: OSI Approved :: Apache Software License
Classifier: Operating System :: POSIX
Classifier: Operating System :: MacOS :: MacOS X
Classifier: Operating System :: POSIX :: Linux
Classifier: Programming Language :: Python :: 3 :: Only
Classifier: Programming Language :: Python :: 3.7
Classifier: Programming Language :: Python :: 3.6
Classifier: Programming Language :: Python :: 3.5
